mitch_dm_mypkg/__init__.py
mitch_dm_mypkg/agroshusayer/__init__.py
mitch_dm_mypkg/agroshusayer/agroshusayer.py
mitch_dm_mypkg/main.py
mitch_dm_mypkg/shusayer/__init__.py
mitch_dm_mypkg/shusayer/shusayer.py
mitch_dm_mypkg-0.1.8.dist-info/entry_points.txt
mitch_dm_mypkg-0.1.8.dist-info/WHEEL
mitch_dm_mypkg-0.1.8.dist-info/METADATA
mitch_dm_mypkg-0.1.8.dist-info/RECORD
